neomt3/__init__.py
neomt3/colab/mt3_reconvat_baseline.ipynb
neomt3/colab/music_transcription_with_transformers.ipynb
neomt3/dataset_processing.py
neomt3/datasets.py
neomt3/event_codec.py
neomt3/event_codec_test.py
neomt3/gin/eval.gin
neomt3/gin/infer.gin
neomt3/gin/ismir2021.gin
neomt3/gin/ismir2022/base.gin
neomt3/gin/ismir2022/finetune.gin
neomt3/gin/ismir2022/pretrain.gin
neomt3/gin/ismir2022/small.gin
neomt3/gin/local_tiny.gin
neomt3/gin/model.gin
neomt3/gin/mt3.gin
neomt3/gin/train.gin
neomt3/inference.py
neomt3/layers.py
neomt3/layers_test.py
neomt3/metrics.py
neomt3/metrics_utils.py
neomt3/metrics_utils_test.py
neomt3/mixing.py
neomt3/models.py
neomt3/network.py
neomt3/note_sequences.py
neomt3/note_sequences_test.py
neomt3/preprocessors.py
neomt3/pytest.ini
neomt3/run_length_encoding.py
neomt3/run_length_encoding_test.py
neomt3/scripts/dump_task.py
neomt3/scripts/extract_monophonic_examples.py
neomt3/spectral_ops.py
neomt3/spectrograms.py
neomt3/summaries.py
neomt3/tasks.py
neomt3/version.py
neomt3/vocabularies.py
neomt3/vocabularies_test.py
neomt3-0.1.1.dist-info/LICENSE
neomt3-0.1.1.dist-info/METADATA
neomt3-0.1.1.dist-info/WHEEL
neomt3-0.1.1.dist-info/entry_points.txt
neomt3-0.1.1.dist-info/RECORD
